sscopes/__init__.py
sscopes/exceptions.py
sscopes/validators.py
sscopes-0.2.0.dist-info/AUTHORS.rst
sscopes-0.2.0.dist-info/LICENSE
sscopes-0.2.0.dist-info/METADATA
sscopes-0.2.0.dist-info/WHEEL
sscopes-0.2.0.dist-info/top_level.txt
sscopes-0.2.0.dist-info/RECORD
