Metadata-Version: 2.1
Name: sscopes
Version: 0.2.0
Summary: Python implementation of Structured Scopes
Home-page: https://github.com/ahopkins/sscopes
Author: Adam Hopkins
Author-email: admhpkns@gmail.com
License: MIT license
Keywords: sscopes
Platform: UNKNOWN
Classifier: Development Status :: 3 - Alpha
Classifier: Intended Audience :: Developers
Classifier: License :: OSI Approved :: MIT License
Classifier: Natural Language :: English
Classifier: Programming Language :: Python :: 3
Classifier: Programming Language :: Python :: 3.5
Classifier: Programming Language :: Python :: 3.6
Classifier: Programming Language :: Python :: 3.7
